Workbook

Sheet LEEME_INICIO
A1: VCF — Toolkit de Pulso Mensual de OKRs (Solo Español)
A2: Fuente única de verdad: MASTER_2026_KRs → OKR_ROLLUP → OnePager_Consejo + Watchlist Horizonte (3 años).
A4: 1) Mensual (Dueños de KR): actualizar KR CRÍTICO? (S/N) (rara vez) y CÓDIGO KR (V/A/R) (mensual) en MASTER_2026_KRs.
A5: 2) Mensual (Comité Gerencial/PMO): revisar OKR_ROLLUP; completar Mensaje 1 línea + Solicitud/Decisión para OKRs en A o R.
A6: 3) Mensual (Consejo): ver OnePager_Consejo (1 página). Conversación = solo excepciones (A/R) + decisiones.
A7: 4) Horizonte 3 años: en ALINEACIÓN_2028_a_2026 definir Cobertura + Ranking (1–5) + Estatus Horizonte (V/A/R) + checkpoint; el OnePager lo muestra.

Sheet MASTER_2026_KRs
A1: MASTER 2026 — OKRs/KRs + Señales Mensuales + Salud del KR
A2: Aquí se captura el estatus mensual de cada KR. Todo lo demás se deriva de esta hoja.
A4: # DE LA INTENCIÓN | B4: INT. DESCRIPCIÓN | C4: OKR ANUAL # | D4: OKR ANUAL ID | E4: KR # | F4: OKR ANUAL DESC (O) | G4: KR ID | H4: KEY RESULT (KR) | I4: META 2026 | J4: REAL OCT. 2025 | K4: REAL ACUM OCT. 2025 | L4: META 1Q 2026 | M4: KR TIPO (Outcome/Driver/Risk) | N4: SEÑAL MENSUAL 1 (Outcome) | O4: SEÑAL MENSUAL 2 (Driver) | P4: SEÑAL MENSUAL 3 (Riesgo/KRI) | Q4: FUENTE / SISTEMA | R4: REGLA G/A/R (simple) | S4: MENSAJE 1-LÍNEA (para Consejo) | T4: ASK / DECISIÓN (si aplica) | U4: KR CRÍTICO? (S/N) | V4: CÓDIGO KR (V/A/R) | W4: PUNTOS (auto) | X4: FECHA ACTUALIZACIÓN (auto)
A5: 1 | B5: Capacidad Transformacional y Diferenciación | C5: 1 | D5: OKR 1 | E5: 1 | F5: Reposicionamiento Estratégico y Diferenciado | G5: KR 1.1 | H5: Alcanzar NPS 8 | I5: 8 | J5: 6 | M5: Outcome | N5: NPS (si se actualiza mensual) o NPS proxy por quejas/servicio | O5: Quejas por 1,000 socios + tendencia | P5: Tiempo de resolución / reincidencia | Q5: CRM / Mesa de servicio | R5: G: tendencia mejora; Y: se estanca; R: empeora 2 meses | S5: Fricción del socio bajo control / requiere acción | T5: — | U5: S | V5: A | W5: =IF(V5="V",0,IF(V5="A",1,IF(V5="R",2,""))) -> 1 | X5: =IF(V5<>"",TODAY(),"") -> 46141
A6: 1 | B6: Capacidad Transformacional y Diferenciación | C6: 1 | D6: OKR 1 | E6: 2 | F6: Reposicionamiento Estratégico y Diferenciado | G6: KR 1.2 | H6: Incrementar cartera bruta 10,771 MDP | I6: 10,771 mdp | M6: Outcome | N6: Cartera bruta (avance vs run-rate) | O6: Pipeline (aprobaciones + originación) | P6: Mora temprana (0-30 / 30-60) | Q6: Core / Crédito / Riesgos | R6: G: >run-rate y mora estable; Y: gap moderado; R: gap alto o mora sube | S6: Crecimiento de cartera en línea / ajustar palancas | T6: Aprobar ajustes de apetito / pricing (si aplica) | U6: N | V6: R | W6: =IF(V6="V",0,IF(V6="A",1,IF(V6="R",2,""))) -> 2 | X6: =IF(V6<>"",TODAY(),"") -> 46141
A7: 1 | B7: Capacidad Transformacional y Diferenciación | C7: 1 | D7: OKR 1 | E7: 3 | F7: Reposicionamiento Estratégico y Diferenciado | G7: KR 1.3 | H7: Incrementar tasa de membresía activa de 33,335 | I7: 33,335 | M7: Outcome | N7: Socios activos netos (altas-bajas) | O7: Tasa de activación 30 días (onboarding) | P7: Churn / dormancia | Q7: Core / Canales | R7: G: neto >run-rate; Y: cerca; R: por debajo 2 meses | S7: Base de socios creciendo de forma saludable | T7: — | U7: S | V7: V | W7: =IF(V7="V",0,IF(V7="A",1,IF(V7="R",2,""))) -> 0 | X7: =IF(V7<>"",TODAY(),"") -> 46141
A8: 1 | B8: Capacidad Transformacional y Diferenciación | C8: 2 | D8: OKR 2 | E8: 4 | F8: Transformación Digital y Eficiencia Operativa | G8: KR 1.4 | H8: Reducir Tasa de Reproceso en la evaluación de los créditos (énfasis en los productos priorizados) del 17% al <13%. | I8: <13% | M8: Driver | N8: % reproceso en evaluación | O8: Tiempo de ciclo de evaluación | P8: Backlog de reprocesos >X días | Q8: Crédito / Operaciones | R8: G: reproceso baja; Y: plano; R: sube | S8: Calidad del flujo de evaluación mejorando | T8: Desbloquear recursos/automatización | U8: N | V8: V | W8: =IF(V8="V",0,IF(V8="A",1,IF(V8="R",2,""))) -> 0 | X8: =IF(V8<>"",TODAY(),"") -> 46141
A9: 1 | B9: Capacidad Transformacional y Diferenciación | C9: 2 | D9: OKR 2 | E9: 5 | F9: Transformación Digital y Eficiencia Operativa | G9: KR 1.5 | H9: Alcanzar y mejorar un cumplimiento SLA Soporte N1 al 80% (Ops.) | I9: 0.8 | M9: Driver | N9: % tickets dentro de SLA | O9: Volumen de incidentes y backlog | P9: Incidentes críticos (Sev 1/2) | Q9: ITSM / Soporte | R9: G: SLA>=meta; Y: 2 semanas bajo; R: incumple 1 mes | S9: Soporte estable / riesgo de interrupciones | T9: Priorizar inversiones / capacity | U9: y | V9: A | W9: =IF(V9="V",0,IF(V9="A",1,IF(V9="R",2,""))) -> 1 | X9: =IF(V9<>"",TODAY(),"") -> 46141
A10: 1 | B10: Capacidad Transformacional y Diferenciación | C10: 2 | D10: OKR 2 | E10: 6 | F10: Transformación Digital y Eficiencia Operativa | G10: KR 1.6 | H10: Mantener la eficiencia operativa de 47.2% | I10: 0.472 | M10: Outcome | N10: Eficiencia operativa (ratio) | O10: Productividad por FTE / automatización | P10: Horas extra / backlog operativo | Q10: Finanzas / Ops | R10: G: mejora vs baseline; Y: leve; R: empeora | S10: Eficiencia bajo control / ajustar ejecución | U10: S | V10: R | W10: =IF(V10="V",0,IF(V10="A",1,IF(V10="R",2,""))) -> 2 | X10: =IF(V10<>"",TODAY(),"") -> 46141
A11: 2 | B11: Crecimiento e Impacto de Mercado | C11: 3 | D11: OKR 3 | E11: 7 | F11: Atraer las nuevas generaciones de socios | G11: KR 2.1 | H11: Aumentar 33,335 nuevos socios activos. | I11: 33,335 | M11: Outcome | N11: Nuevos socios activos vs run-rate | O11: Conversión del funnel (lead→alta→activo) | P11: Abandono onboarding / cancelaciones | Q11: CRM / Canales / Core | R11: G: >run-rate; Y: cerca; R: <run-rate 2 meses | S11: Crecimiento de socios en marcha | T11: — | U11: N | V11: V | W11: =IF(V11="V",0,IF(V11="A",1,IF(V11="R",2,""))) -> 0 | X11: =IF(V11<>"",TODAY(),"") -> 46141
A12: 2 | B12: Crecimiento e Impacto de Mercado | C12: 3 | D12: OKR 3 | E12: 8 | F12: Atraer las nuevas generaciones de socios | G12: KR 2.2 | H12: Lograr que 35% de los nuevos socios provengan de las 3 regiones estratégicas prioritarias. | I12: 0.35 | M12: Outcome | N12: % nuevos socios segmento joven | O12: Leads jóvenes + conversión | P12: CAC / eficacia campañas | Q12: Marketing / CRM | R12: G: %>=meta; Y: ligeramente bajo; R: bajo 2 meses | S12: Atractivo para jóvenes: on/off track | T12: Ajuste de inversión comercial | U12: N | V12: A | W12: =IF(V12="V",0,IF(V12="A",1,IF(V12="R",2,""))) -> 1 | X12: =IF(V12<>"",TODAY(),"") -> 46141
A13: 2 | B13: Crecimiento e Impacto de Mercado | C13: 3 | D13: OKR 3 | E13: 9 | F13: Atraer las nuevas generaciones de socios | G13: KR 2.3 | H13: Alcanzar que 25% de los nuevos socios jóvenes (4166) completen onboarding digital | I13: 4166 | M13: Driver | N13: % jóvenes completan onboarding digital | O13: Tasa de éxito digital (login/registro/validación) | P13: Errores en app / caídas | Q13: Digital / TI | R13: G: éxito>=meta; Y: caídas puntuales; R: fallas sostenidas | S13: Onboarding digital habilitando crecimiento joven | T13: Priorizar fixes digitales | U13: S | V13: A | W13: =IF(V13="V",0,IF(V13="A",1,IF(V13="R",2,""))) -> 1 | X13: =IF(V13<>"",TODAY(),"") -> 46141
A14: 2 | B14: Crecimiento e Impacto de Mercado | C14: 4 | D14: OKR 4 | E14: 10 | F14: Modelo Comercial Sustentable y Sostenible | G14: KR 2.4 | H14: Alcanzar desembolso 7200 mdp annual (600 mdp mensual). | I14: 7200 | M14: Outcome | N14: Desembolso mensual vs 600 mdp run-rate | O14: Pipeline cobertura (3x) | P14: Mora/ROI por cohorte | Q14: Crédito / Finanzas | R14: G: run-rate y calidad; Y: gap; R: gap alto/mora sube | S14: Modelo comercial ejecutando sin comprometer riesgo | T14: Ajustes de política/apetito | U14: N | V14: V | W14: =IF(V14="V",0,IF(V14="A",1,IF(V14="R",2,""))) -> 0 | X14: =IF(V14<>"",TODAY(),"") -> 46141
A15: 3 | B15: Gestión y cultura de Riesgos | C15: 5 | D15: OKR 5 | E15: 11 | F15: Consolidar un Marco Institucional de Apetito de Riesgo que oriente la toma de decisiones en todos los niveles | G15: KR 3.1 | H15: Obtener la aprobación de la Declaratoria de Apetito de Riesgo por parte del Consejo de Administración. (Enero 2026) | I15: Declaratoria de Apetito aprobada en Enero 2026 | M15: Outcome | N15: Hitos completados declaratoria (plan) | O15: % stakeholders firmados | P15: Riesgos abiertos sin cierre | Q15: Gobierno / Riesgos | R15: G: hito del mes completo; Y: atraso leve; R: atraso crítico | S15: Apetito de riesgo: avance/atraso | T15: Decisión/validación del Consejo | U15: N | V15: V | W15: =IF(V15="V",0,IF(V15="A",1,IF(V15="R",2,""))) -> 0 | X15: =IF(V15<>"",TODAY(),"") -> 46141
A16: 3 | B16: Gestión y cultura de Riesgos | C16: 5 | D16: OKR 5 | E16: 12 | F16: Consolidar un Marco Institucional de Apetito de Riesgo que oriente la toma de decisiones en todos los niveles | G16: KR 3.2 | H16: Cuantificar al menos el 30 % de los riesgos prioritarios mediante modelos avanzados y validados | I16: TBD | M16: Outcome | N16: % riesgos prioritarios cuantificados | O16: # escenarios/modelos validados | P16: Brecha de datos / modelos vencidos | Q16: Riesgos / Datos | R16: G: % sube; Y: plano; R: baja o no avanza | S16: Cuantificación de riesgos en marcha | T16: Recursos/datos prioritarios | U16: N | V16: V | W16: =IF(V16="V",0,IF(V16="A",1,IF(V16="R",2,""))) -> 0 | X16: =IF(V16<>"",TODAY(),"") -> 46141
A17: 3 | B17: Gestión y cultura de Riesgos | C17: 5 | D17: OKR 5 | E17: 13 | F17: Consolidar un Marco Institucional de Apetito de Riesgo que oriente la toma de decisiones en todos los niveles | G17: KR 3.3 | H17: Alcanzar un mínimo de 5 decisiones estratégicas respaldadas por alertas o insights derivados de los límites de riesgo. | I17: TBD | M17: Outcome | N17: # decisiones usando apetito (acumulado) | O17: # excepciones escaladas/resueltas | P17: Decisiones retrasadas >X días | Q17: Consejo/Comité | R17: G: ≥run-rate; Y: cerca; R: bajo | S17: Apetito usado en decisiones reales | T17: Alineación/decisión | U17: S | V17: V | W17: =IF(V17="V",0,IF(V17="A",1,IF(V17="R",2,""))) -> 0 | X17: =IF(V17<>"",TODAY(),"") -> 46141
A18: 3 | B18: Gestión y cultura de Riesgos | C18: 6 | D18: OKR 6 | E18: 14 | F18: Fortalecer la resiliencia organizacional y una cultura de riesgo ética y proactiva | G18: KR 3.4 | H18: Lograr que al menos el 50 % de las alertas de riesgo sean generadas por la primera línea de defensa. | I18: TBD | M18: Driver | N18: % alertas en fase temprana | O18: Cobertura de controles / monitoreo | P18: Incidentes operacionales | Q18: Riesgos / Operaciones | R18: G: % sube; Y: plano; R: baja | S18: Detección temprana está mejorando | T18: Invertir en controles | U18: N | V18: V | W18: =IF(V18="V",0,IF(V18="A",1,IF(V18="R",2,""))) -> 0 | X18: =IF(V18<>"",TODAY(),"") -> 46141
A19: 3 | B19: Gestión y cultura de Riesgos | C19: 6 | D19: OKR 6 | E19: 15 | F19: Fortalecer la resiliencia organizacional y una cultura de riesgo ética y proactiva | G19: KR 3.5 | H19: Alcanzar el tiempo promedio de respuesta ante riesgos críticos a 72 horas o menos. | I19: <72 hrs | M19: Outcome | N19: Tiempo promedio respuesta a incidentes | O19: % dentro de 72 hrs | P19: Backlog incidentes abiertos | Q19: Riesgos / Operaciones | R19: G: cumple; Y: 1-2 casos fuera; R: incumple | S19: Respuesta a incidentes bajo control | T19: — | U19: N | V19: V | W19: =IF(V19="V",0,IF(V19="A",1,IF(V19="R",2,""))) -> 0 | X19: =IF(V19<>"",TODAY(),"") -> 46141
A20: 4 | B20: Excelencia en Liderazgo, Cultura y Gobernanza | C20: 7 | D20: OKR 7 | E20: 16 | F20: Generación de Liderazgo Estratégico y Adaptativo | G20: KR 4.1 | H20: Alcanzar Avance Plan estratégico 80%. | I20: 0.8 | M20: Outcome | N20: % avance plan (epics/OKRs) | O20: % compromisos en verde (OKR health) | P20: Bloqueos críticos / dependencias | Q20: PMO / Estrategia | R20: G: avance >=plan; Y: atraso leve; R: atraso 2 meses | S20: Ejecución del plan en ruta / requiere desbloqueo | T20: Decisión sobre tradeoffs | U20: N | V20: A | W20: =IF(V20="V",0,IF(V20="A",1,IF(V20="R",2,""))) -> 1 | X20: =IF(V20<>"",TODAY(),"") -> 46141
A21: 4 | B21: Excelencia en Liderazgo, Cultura y Gobernanza | C21: 7 | D21: OKR 7 | E21: 17 | F21: Generación de Liderazgo Estratégico y Adaptativo | G21: KR 4.2 | H21: Incrementar evaluación del comportamiento Liderazgo de 77% al 80% | I21: >=77% | M21: Driver | N21: Cumplimiento prácticas liderazgo (proxy) | O21: Cobertura 1:1 / rutinas de liderazgo | P21: Rotación / ausentismo | Q21: RH / Ops | R21: G: proxies suben; Y: mixto; R: caen | S21: Postura de liderazgo: señales tempranas | T21: — | U21: S | V21: V | W21: =IF(V21="V",0,IF(V21="A",1,IF(V21="R",2,""))) -> 0 | X21: =IF(V21<>"",TODAY(),"") -> 46141
A22: 4 | B22: Excelencia en Liderazgo, Cultura y Gobernanza | C22: 7 | D22: OKR 7 | E22: 18 | F22: Generación de Liderazgo Estratégico y Adaptativo | G22: KR 4.3 | H22: Alcanzar roles clave con plan de sucesión activo 80%. | I22: 80% | M22: Outcome | N22: % roles clave con sucesor activo | O22: Readiness del sucesor | P22: Vacantes críticas | Q22: RH | R22: G: % sube; Y: plano; R: baja | S22: Sucesión avanzando / riesgo en roles clave | T22: — | U22: N | V22: V | W22: =IF(V22="V",0,IF(V22="A",1,IF(V22="R",2,""))) -> 0 | X22: =IF(V22<>"",TODAY(),"") -> 46141
A23: 4 | B23: Excelencia en Liderazgo, Cultura y Gobernanza | C23: 8 | D23: OKR 8 | E23: 19 | F23: Gobernanza orientada a la Sostenibilidad Corporativa | G23: KR 4.4 | H23: Incrementar Indicador de satisfacción de clima laboral global de 67% al 71%. | I23: 71% | M23: Outcome | N23: Clima (medición trimestral) + proxy mensual | O23: Ausentismo + rotación voluntaria | P23: Quejas internas / incidentes | Q23: RH / Gente | R23: G: proxies sanos; Y: alerta; R: deterioro | S23: Ambiente interno: anticipación temprana | T23: — | U23: S | V23: V | W23: =IF(V23="V",0,IF(V23="A",1,IF(V23="R",2,""))) -> 0 | X23: =IF(V23<>"",TODAY(),"") -> 46141
A24: 4 | B24: Excelencia en Liderazgo, Cultura y Gobernanza | C24: 8 | D24: OKR 8 | E24: 20 | F24: Gobernanza orientada a la Sostenibilidad Corporativa | G24: KR 4.5 | H24: Incrementar eNPS de 8.4 a 8.6 de 10. | I24: 8.6 | M24: Outcome | N24: eNPS (trimestral) + pulso operativo mensual | O24: Drivers: carga de trabajo/claridad | P24: Rotación/absentismo | Q24: RH / Pulso | R24: G: índice mejora; Y: estable; R: baja | S24: Energía del equipo: bajo control / riesgo | T24: — | U24: N | V24: V | W24: =IF(V24="V",0,IF(V24="A",1,IF(V24="R",2,""))) -> 0 | X24: =IF(V24<>"",TODAY(),"") -> 46141
A25: 4 | B25: Excelencia en Liderazgo, Cultura y Gobernanza | C25: 8 | D25: OKR 8 | E25: 21 | F25: Gobernanza orientada a la Sostenibilidad Corporativa | G25: KR 4.6 | H25: Satisfaccion de Stakeholders de 0 (primera base) a 8. | I25: 8 | M25: Outcome | N25: Satisfacción de stakeholders (trimestral) | O25: Tiempo respuesta + SLA a stakeholders | P25: Escalaciones abiertas | Q25: Gobierno / Servicio | R25: G: tendencia positiva; Y: plana; R: negativa | S25: Relación con stakeholders en ruta | T25: — | U25: N | V25: V | W25: =IF(V25="V",0,IF(V25="A",1,IF(V25="R",2,""))) -> 0 | X25: =IF(V25<>"",TODAY(),"") -> 46141

Sheet OKR_ROLLUP
A1: OKR_ROLLUP — Consolidación automática (KR → OKR Anual)
A2: Estatus usa VAR (Verde/Ámbar/Rojo) con gate de KR Crítico + reglas de mezcla.
A4: Intención # | B4: Intención | C4: OKR # (Anual) | D4: Objetivo (OKR Anual) | E4: KRs | F4: #V | G4: #A | H4: #R | I4: Críticos R | J4: Críticos A | K4: Estatus (V/A/R) | L4: Índice de Salud (0-100) | M4: Tendencia (↑/→/↓) | N4: Confianza (Alta/Media/Baja) | O4: Mensaje 1 línea (para Consejo) | P4: Solicitud/Decisión (si aplica)
A5: 1 | B5: Capacidad Transformacional y Diferenciación | C5: 1 | D5: Reposicionamiento Estratégico y Diferenciado | E5: =COUNTIF(MASTER_2026_KRs!$C:$C,C5) -> 3 | F5: =COUNTIFS(MASTER_2026_KRs!$C:$C,C5,MASTER_2026_KRs!$V:$V,"V") -> 1 | G5: =COUNTIFS(MASTER_2026_KRs!$C:$C,C5,MASTER_2026_KRs!$V:$V,"A") -> 1 | H5: =COUNTIFS(MASTER_2026_KRs!$C:$C,C5,MASTER_2026_KRs!$V:$V,"R") -> 1 | I5: =COUNTIFS(MASTER_2026_KRs!$C:$C,C5,MASTER_2026_KRs!$V:$V,"R",MASTER_2026_KRs!$U:$U,"S") -> 0 | J5: =COUNTIFS(MASTER_2026_KRs!$C:$C,C5,MASTER_2026_KRs!$V:$V,"A",MASTER_2026_KRs!$U:$U,"S") -> 1 | K5: =IF(I5>0,"R",IF(J5>0,"A",IF(E5=1,IF(H5=1,"R",IF(G5=1,"A","V")),IF(E5=2,IF(H5>=1,IF(G5+H5>=2,"R","A"),IF(G5=2,"R",IF(G5=1,"A","V"))),IF(E5=3,IF(H5>=1,IF(G5+H5>=2,"R","A"),IF(G5>=2,"A","V")),""))))) -> A | L5: =IF(E5="","",ROUND(100-((G5+2*H5)/(2*E5))*100,0)) -> 50 | M5: ↓ | N5: Baja | O5: Help Me - SoS - Ayuda | P5: Recomendar Experto Actuario
A6: 1 | B6: Capacidad Transformacional y Diferenciación | C6: 2 | D6: Transformación Digital y Eficiencia Operativa | E6: =COUNTIF(MASTER_2026_KRs!$C:$C,C6) -> 3 | F6: =COUNTIFS(MASTER_2026_KRs!$C:$C,C6,MASTER_2026_KRs!$V:$V,"V") -> 1 | G6: =COUNTIFS(MASTER_2026_KRs!$C:$C,C6,MASTER_2026_KRs!$V:$V,"A") -> 1 | H6: =COUNTIFS(MASTER_2026_KRs!$C:$C,C6,MASTER_2026_KRs!$V:$V,"R") -> 1 | I6: =COUNTIFS(MASTER_2026_KRs!$C:$C,C6,MASTER_2026_KRs!$V:$V,"R",MASTER_2026_KRs!$U:$U,"S") -> 1 | J6: =COUNTIFS(MASTER_2026_KRs!$C:$C,C6,MASTER_2026_KRs!$V:$V,"A",MASTER_2026_KRs!$U:$U,"S") -> 0 | K6: =IF(I6>0,"R",IF(J6>0,"A",IF(E6=1,IF(H6=1,"R",IF(G6=1,"A","V")),IF(E6=2,IF(H6>=1,IF(G6+H6>=2,"R","A"),IF(G6=2,"R",IF(G6=1,"A","V"))),IF(E6=3,IF(H6>=1,IF(G6+H6>=2,"R","A"),IF(G6>=2,"A","V")),""))))) -> R | L6: =IF(E6="","",ROUND(100-((G6+2*H6)/(2*E6))*100,0)) -> 50 | M6: ↓ | N6: Baja | O6: Help Me - SoS - Ayuda | P6: Activamos nuevo canal alternativo
A7: 2 | B7: Crecimiento e Impacto de Mercado | C7: 3 | D7: Atraer las nuevas generaciones de socios | E7: =COUNTIF(MASTER_2026_KRs!$C:$C,C7) -> 3 | F7: =COUNTIFS(MASTER_2026_KRs!$C:$C,C7,MASTER_2026_KRs!$V:$V,"V") -> 1 | G7: =COUNTIFS(MASTER_2026_KRs!$C:$C,C7,MASTER_2026_KRs!$V:$V,"A") -> 2 | H7: =COUNTIFS(MASTER_2026_KRs!$C:$C,C7,MASTER_2026_KRs!$V:$V,"R") -> 0 | I7: =COUNTIFS(MASTER_2026_KRs!$C:$C,C7,MASTER_2026_KRs!$V:$V,"R",MASTER_2026_KRs!$U:$U,"S") -> 0 | J7: =COUNTIFS(MASTER_2026_KRs!$C:$C,C7,MASTER_2026_KRs!$V:$V,"A",MASTER_2026_KRs!$U:$U,"S") -> 1 | K7: =IF(I7>0,"R",IF(J7>0,"A",IF(E7=1,IF(H7=1,"R",IF(G7=1,"A","V")),IF(E7=2,IF(H7>=1,IF(G7+H7>=2,"R","A"),IF(G7=2,"R",IF(G7=1,"A","V"))),IF(E7=3,IF(H7>=1,IF(G7+H7>=2,"R","A"),IF(G7>=2,"A","V")),""))))) -> A | L7: =IF(E7="","",ROUND(100-((G7+2*H7)/(2*E7))*100,0)) -> 67 | M7: → | N7: Media | O7: Plan de mitigacion activado | P7: Creamos task force para resolucion de los sangramientos operativos
A8: 2 | B8: Crecimiento e Impacto de Mercado | C8: 4 | D8: Modelo Comercial Sustentable y Sostenible | E8: =COUNTIF(MASTER_2026_KRs!$C:$C,C8) -> 1 | F8: =COUNTIFS(MASTER_2026_KRs!$C:$C,C8,MASTER_2026_KRs!$V:$V,"V") -> 1 | G8: =COUNTIFS(MASTER_2026_KRs!$C:$C,C8,MASTER_2026_KRs!$V:$V,"A") -> 0 | H8: =COUNTIFS(MASTER_2026_KRs!$C:$C,C8,MASTER_2026_KRs!$V:$V,"R") -> 0 | I8: =COUNTIFS(MASTER_2026_KRs!$C:$C,C8,MASTER_2026_KRs!$V:$V,"R",MASTER_2026_KRs!$U:$U,"S") -> 0 | J8: =COUNTIFS(MASTER_2026_KRs!$C:$C,C8,MASTER_2026_KRs!$V:$V,"A",MASTER_2026_KRs!$U:$U,"S") -> 0 | K8: =IF(I8>0,"R",IF(J8>0,"A",IF(E8=1,IF(H8=1,"R",IF(G8=1,"A","V")),IF(E8=2,IF(H8>=1,IF(G8+H8>=2,"R","A"),IF(G8=2,"R",IF(G8=1,"A","V"))),IF(E8=3,IF(H8>=1,IF(G8+H8>=2,"R","A"),IF(G8>=2,"A","V")),""))))) -> V | L8: =IF(E8="","",ROUND(100-((G8+2*H8)/(2*E8))*100,0)) -> 100 | M8: ↑ | N8: Alta | O8: Monitoreando
A9: 3 | B9: Gestión y cultura de Riesgos | C9: 5 | D9: Consolidar un Marco Institucional de Apetito de Riesgo que oriente la toma de decisiones en todos los niveles | E9: =COUNTIF(MASTER_2026_KRs!$C:$C,C9) -> 3 | F9: =COUNTIFS(MASTER_2026_KRs!$C:$C,C9,MASTER_2026_KRs!$V:$V,"V") -> 3 | G9: =COUNTIFS(MASTER_2026_KRs!$C:$C,C9,MASTER_2026_KRs!$V:$V,"A") -> 0 | H9: =COUNTIFS(MASTER_2026_KRs!$C:$C,C9,MASTER_2026_KRs!$V:$V,"R") -> 0 | I9: =COUNTIFS(MASTER_2026_KRs!$C:$C,C9,MASTER_2026_KRs!$V:$V,"R",MASTER_2026_KRs!$U:$U,"S") -> 0 | J9: =COUNTIFS(MASTER_2026_KRs!$C:$C,C9,MASTER_2026_KRs!$V:$V,"A",MASTER_2026_KRs!$U:$U,"S") -> 0 | K9: =IF(I9>0,"R",IF(J9>0,"A",IF(E9=1,IF(H9=1,"R",IF(G9=1,"A","V")),IF(E9=2,IF(H9>=1,IF(G9+H9>=2,"R","A"),IF(G9=2,"R",IF(G9=1,"A","V"))),IF(E9=3,IF(H9>=1,IF(G9+H9>=2,"R","A"),IF(G9>=2,"A","V")),""))))) -> V | L9: =IF(E9="","",ROUND(100-((G9+2*H9)/(2*E9))*100,0)) -> 100 | M9: → | N9: Alta | O9: Monitoreando
A10: 3 | B10: Gestión y cultura de Riesgos | C10: 6 | D10: Fortalecer la resiliencia organizacional y una cultura de riesgo ética y proactiva | E10: =COUNTIF(MASTER_2026_KRs!$C:$C,C10) -> 2 | F10: =COUNTIFS(MASTER_2026_KRs!$C:$C,C10,MASTER_2026_KRs!$V:$V,"V") -> 2 | G10: =COUNTIFS(MASTER_2026_KRs!$C:$C,C10,MASTER_2026_KRs!$V:$V,"A") -> 0 | H10: =COUNTIFS(MASTER_2026_KRs!$C:$C,C10,MASTER_2026_KRs!$V:$V,"R") -> 0 | I10: =COUNTIFS(MASTER_2026_KRs!$C:$C,C10,MASTER_2026_KRs!$V:$V,"R",MASTER_2026_KRs!$U:$U,"S") -> 0 | J10: =COUNTIFS(MASTER_2026_KRs!$C:$C,C10,MASTER_2026_KRs!$V:$V,"A",MASTER_2026_KRs!$U:$U,"S") -> 0 | K10: =IF(I10>0,"R",IF(J10>0,"A",IF(E10=1,IF(H10=1,"R",IF(G10=1,"A","V")),IF(E10=2,IF(H10>=1,IF(G10+H10>=2,"R","A"),IF(G10=2,"R",IF(G10=1,"A","V"))),IF(E10=3,IF(H10>=1,IF(G10+H10>=2,"R","A"),IF(G10>=2,"A","V")),""))))) -> V | L10: =IF(E10="","",ROUND(100-((G10+2*H10)/(2*E10))*100,0)) -> 100 | M10: ↓ | N10: Alta | O10: Monitoreando
A11: 4 | B11: Excelencia en Liderazgo, Cultura y Gobernanza | C11: 7 | D11: Generación de Liderazgo Estratégico y Adaptativo | E11: =COUNTIF(MASTER_2026_KRs!$C:$C,C11) -> 3 | F11: =COUNTIFS(MASTER_2026_KRs!$C:$C,C11,MASTER_2026_KRs!$V:$V,"V") -> 2 | G11: =COUNTIFS(MASTER_2026_KRs!$C:$C,C11,MASTER_2026_KRs!$V:$V,"A") -> 1 | H11: =COUNTIFS(MASTER_2026_KRs!$C:$C,C11,MASTER_2026_KRs!$V:$V,"R") -> 0 | I11: =COUNTIFS(MASTER_2026_KRs!$C:$C,C11,MASTER_2026_KRs!$V:$V,"R",MASTER_2026_KRs!$U:$U,"S") -> 0 | J11: =COUNTIFS(MASTER_2026_KRs!$C:$C,C11,MASTER_2026_KRs!$V:$V,"A",MASTER_2026_KRs!$U:$U,"S") -> 0 | K11: =IF(I11>0,"R",IF(J11>0,"A",IF(E11=1,IF(H11=1,"R",IF(G11=1,"A","V")),IF(E11=2,IF(H11>=1,IF(G11+H11>=2,"R","A"),IF(G11=2,"R",IF(G11=1,"A","V"))),IF(E11=3,IF(H11>=1,IF(G11+H11>=2,"R","A"),IF(G11>=2,"A","V")),""))))) -> V | L11: =IF(E11="","",ROUND(100-((G11+2*H11)/(2*E11))*100,0)) -> 83 | M11: ↑ | N11: Alta | O11: Monitoreando
A12: 4 | B12: Excelencia en Liderazgo, Cultura y Gobernanza | C12: 8 | D12: Gobernanza orientada a la Sostenibilidad Corporativa | E12: =COUNTIF(MASTER_2026_KRs!$C:$C,C12) -> 3 | F12: =COUNTIFS(MASTER_2026_KRs!$C:$C,C12,MASTER_2026_KRs!$V:$V,"V") -> 3 | G12: =COUNTIFS(MASTER_2026_KRs!$C:$C,C12,MASTER_2026_KRs!$V:$V,"A") -> 0 | H12: =COUNTIFS(MASTER_2026_KRs!$C:$C,C12,MASTER_2026_KRs!$V:$V,"R") -> 0 | I12: =COUNTIFS(MASTER_2026_KRs!$C:$C,C12,MASTER_2026_KRs!$V:$V,"R",MASTER_2026_KRs!$U:$U,"S") -> 0 | J12: =COUNTIFS(MASTER_2026_KRs!$C:$C,C12,MASTER_2026_KRs!$V:$V,"A",MASTER_2026_KRs!$U:$U,"S") -> 0 | K12: =IF(I12>0,"R",IF(J12>0,"A",IF(E12=1,IF(H12=1,"R",IF(G12=1,"A","V")),IF(E12=2,IF(H12>=1,IF(G12+H12>=2,"R","A"),IF(G12=2,"R",IF(G12=1,"A","V"))),IF(E12=3,IF(H12>=1,IF(G12+H12>=2,"R","A"),IF(G12>=2,"A","V")),""))))) -> V | L12: =IF(E12="","",ROUND(100-((G12+2*H12)/(2*E12))*100,0)) -> 100 | M12: → | N12: Alta | O12: Monitoreando

Sheet ALINEACIÓN_2028_a_2026
A1: ALINEACIÓN 2028→2026 — Cobertura de KRs 3 años + Watchlist Horizonte
A2: Clasifica los KRs 3 años y selecciona Top 1–5 para visibilidad mensual en el OnePager del Consejo.
A4: Intención | B4: KR ID 2028 | C4: KR 2028 (Largo plazo) | D4: Habilitadores 2026 (OKR/KR) | E4: Gap / Notas | F4: Decisión de Cobertura | G4: Proxy Año 1 (si aplica) | H4: Cadencia | I4: Ranking Watchlist (1-5) | J4: Estatus Horizonte (V/A/R) | K4: Próximo checkpoint (fecha) | L4: Mensaje 1 línea | M4: Solicitud/Decisión
A5: 1 | B5: KR 1 | C5: Mejorar eficiencia operativa al 30% | D5: OKR 2 / KR 1.4-1.6 | E5: Alinear a costo/ingreso y productividad; KR 1.6 es core | F5: Cubierto | H5: Mensual | I5: 1 | J5: R | K5: 46081 | L5: Externo Analysis del Problema activado | M5: Aprobar plan de correction de corto plazo
A6: 1 | B6: KR 2 | C6: Aumentar Participación de Mercado 3.6 a 4.5% | D6: OKR 1 / KR 1.2-1.3 + OKR 3/KR 2.1 | E6: Evitar duplicidad 33,335; definir indicador de market share mensual | F6: Cubierto | H6: Mensual | I6: 2 | J6: A | K6: 46099 | L6: Campana para nuevos socios se debe cambiar a otro mercado basado en resultados preliminares | M6: Aprobar Presupuesto y establecer gatillos de escalamiento
A7: 1 | B7: KR 3 | C7: Mantener NPS a 8 | D7: OKR 1 / KR 1.1 + Pulse NPS (servicio) | E7: NPS anual: usar proxies mensuales (quejas, resolución, FCR) | F7: Cubierto | H7: Mensual | I7: 3 | J7: V | K7: 46120 | L7: Monitoreando
A8: 2 | B8: KR 1 | C8: Incrementar activos totales a MXN $21 mil mdp | D8: OKR 1/KR 1.2 + OKR 4/KR 2.4 | E8: Agregar indicador mensual de activos/depósitos; hoy no está explícito | F8: Cubierto | H8: Mensual | I8: 4 | J8: A | K8: 46080 | L8: Asignacion a Comision Comercial para profundizar entendimiento de los problemas | M8: Establecer prioridades para los cambios del plan de captacion
A9: 2 | B9: KR 2 | C9: Mantener mora <=8% | D9: (no directo) | E9: (Añadir KPI mensual) | F9: Requiere Proxy Año 1 | H9: Mensual | I9: 5 | J9: A | K9: 46112 | L9: Cobranza perdio 15% de la estructura este mes | M9: Aprovar proveedor para corto plazo
A10: 2 | B10: KR 3 | C10: Crecer en 100,000 nuevos socios activos | D10: OKR 3 / KR 2.1 | E10: OK | F10: Cubierto | H10: Mensual | I10: 6 | J10: V
A11: 2 | B11: KR 4 | C11: 50% nuevos socios segmento joven | D11: OKR 3 / KR 2.2 | E11: OK | F11: Cubierto | H11: Mensual | I11: 7 | J11: V
A12: 2 | B12: KR 5 | C12: 25% socios jóvenes onboarding digital | D12: OKR 3 / KR 2.3 | E12: OK | F12: Cubierto | H12: Mensual | I12: 8 | J12: V
A13: 2 | B13: KR 6 | C13: Mantener ROA 5% | D13: (no directo) | E13: (Añadir KPI mensual) | F13: Requiere Proxy Año 1 | H13: Mensual | I13: 9 | J13: V
A14: 3 | B14: KR 1 | C14: Riesgos con límites cuantificados | D14: OKR 5 / KR 3.1-3.3 | E14: TBDs deben definirse en enero; llevar al Consejo para validación | F14: Cubierto | H14: Mensual | I14: 10 | J14: V
A15: 3 | B15: KR 2 | C15: Pérdidas operacionales <=1.5% (55 mdp) | D15: (no directo) | E15: (Añadir KPI mensual) | F15: Requiere Proxy Año 1 | H15: Mensual | I15: 11 | J15: V
A16: 3 | B16: KR 3 | C16: Eventos identificados temprano >=50% | D16: OKR 6 / KR 3.4-3.5 | E16: OK | F16: Cubierto | H16: Mensual | I16: 12 | J16: V
A17: 4 | B17: KR 4.5 | C17: Mantener eNPS | D17: OKR 8 / KR 4.5 + Pulso Operativo | E17: Conectar pulso mensual a eNPS trimestral/anual | F17: Cubierto | H17: Mensual | I17: 13 | J17: V
A18: 4 | B18: KR 4.3 | C18: Plan de sucesión puestos clave | D18: OKR 7 / KR 4.3 | E18: OK | F18: Cubierto | H18: Mensual | I18: 14 | J18: V
A19: 4 | B19: KR 4.6 | C19: Salud organizacional interna | D19: OKR 8 / KR 4.6 | E19: Definir claramente índice (hoy meta 0.003 en 2028 sheet) | F19: Cubierto | H19: Mensual | I19: 15 | J19: V
A20: 4 | B20: KR 4.4 | C20: Clima laboral | D20: OKR 8 / KR 4.4 | E20: Corregir meta 71% | F20: Cubierto | H20: Mensual | I20: 16 | J20: V
A21: 4 | B21: KR 4.7 | C21: Rotación de personal | D21: (no directo) | E21: (Añadir KPI mensual) | F21: Requiere Proxy Año 1 | H21: Mensual | I21: 17 | J21: V
A22: 4 | B22: KR 4.1 | C22: Avance plan estratégico | D22: OKR 7 / KR 4.1 | E22: OK | F22: Cubierto | H22: Mensual | I22: 18 | J22: V

Sheet OnePager_Consejo
B1: VCF — Pulso Mensual de OKRs (Vista para Consejo)
B2: Mensual: OKRs 1 año (pulso). Horizonte: Top 1–5 KRs 3 años. Conversación = excepciones + decisiones.
B4: OKR | C4: Objetivo (OKR Anual) | D4: Estatus (V/A/R) | E4: Tendencia | F4: Confianza | G4: Mensaje (1 línea) | H4: Solicitud/Decisión
B5: 1 | C5: =IFERROR(INDEX(OKR_ROLLUP!$D:$D, MATCH($B5, OKR_ROLLUP!$C:$C, 0)),"") -> Reposicionamiento Estratégico y Diferenciado | D5: =IFERROR(INDEX(OKR_ROLLUP!$K:$K, MATCH($B5, OKR_ROLLUP!$C:$C, 0)),"") -> A | E5: =IFERROR(INDEX(OKR_ROLLUP!$M:$M, MATCH($B5, OKR_ROLLUP!$C:$C, 0)),"") -> ↓ | F5: =IFERROR(INDEX(OKR_ROLLUP!$N:$N, MATCH($B5, OKR_ROLLUP!$C:$C, 0)),"") -> Baja | G5: =IFERROR(INDEX(OKR_ROLLUP!$O:$O, MATCH($B5, OKR_ROLLUP!$C:$C, 0)),"") -> Help Me - SoS - Ayuda | H5: =IFERROR(INDEX(OKR_ROLLUP!$P:$P, MATCH($B5, OKR_ROLLUP!$C:$C, 0)),"") -> Recomendar Experto Actuario
B6: 2 | C6: =IFERROR(INDEX(OKR_ROLLUP!$D:$D, MATCH($B6, OKR_ROLLUP!$C:$C, 0)),"") -> Transformación Digital y Eficiencia Operativa | D6: =IFERROR(INDEX(OKR_ROLLUP!$K:$K, MATCH($B6, OKR_ROLLUP!$C:$C, 0)),"") -> R | E6: =IFERROR(INDEX(OKR_ROLLUP!$M:$M, MATCH($B6, OKR_ROLLUP!$C:$C, 0)),"") -> ↓ | F6: =IFERROR(INDEX(OKR_ROLLUP!$N:$N, MATCH($B6, OKR_ROLLUP!$C:$C, 0)),"") -> Baja | G6: =IFERROR(INDEX(OKR_ROLLUP!$O:$O, MATCH($B6, OKR_ROLLUP!$C:$C, 0)),"") -> Help Me - SoS - Ayuda | H6: =IFERROR(INDEX(OKR_ROLLUP!$P:$P, MATCH($B6, OKR_ROLLUP!$C:$C, 0)),"") -> Activamos nuevo canal alternativo
B7: 3 | C7: =IFERROR(INDEX(OKR_ROLLUP!$D:$D, MATCH($B7, OKR_ROLLUP!$C:$C, 0)),"") -> Atraer las nuevas generaciones de socios | D7: =IFERROR(INDEX(OKR_ROLLUP!$K:$K, MATCH($B7, OKR_ROLLUP!$C:$C, 0)),"") -> A | E7: =IFERROR(INDEX(OKR_ROLLUP!$M:$M, MATCH($B7, OKR_ROLLUP!$C:$C, 0)),"") -> → | F7: =IFERROR(INDEX(OKR_ROLLUP!$N:$N, MATCH($B7, OKR_ROLLUP!$C:$C, 0)),"") -> Media | G7: =IFERROR(INDEX(OKR_ROLLUP!$O:$O, MATCH($B7, OKR_ROLLUP!$C:$C, 0)),"") -> Plan de mitigacion activado | H7: =IFERROR(INDEX(OKR_ROLLUP!$P:$P, MATCH($B7, OKR_ROLLUP!$C:$C, 0)),"") -> Creamos task force para resolucion de los sangramientos operativos
B8: 4 | C8: =IFERROR(INDEX(OKR_ROLLUP!$D:$D, MATCH($B8, OKR_ROLLUP!$C:$C, 0)),"") -> Modelo Comercial Sustentable y Sostenible | D8: =IFERROR(INDEX(OKR_ROLLUP!$K:$K, MATCH($B8, OKR_ROLLUP!$C:$C, 0)),"") -> V | E8: =IFERROR(INDEX(OKR_ROLLUP!$M:$M, MATCH($B8, OKR_ROLLUP!$C:$C, 0)),"") -> ↑ | F8: =IFERROR(INDEX(OKR_ROLLUP!$N:$N, MATCH($B8, OKR_ROLLUP!$C:$C, 0)),"") -> Alta | G8: =IFERROR(INDEX(OKR_ROLLUP!$O:$O, MATCH($B8, OKR_ROLLUP!$C:$C, 0)),"") -> Monitoreando | H8: =IFERROR(INDEX(OKR_ROLLUP!$P:$P, MATCH($B8, OKR_ROLLUP!$C:$C, 0)),"") -> 0
B9: 5 | C9: =IFERROR(INDEX(OKR_ROLLUP!$D:$D, MATCH($B9, OKR_ROLLUP!$C:$C, 0)),"") -> Consolidar un Marco Institucional de Apetito de Riesgo que oriente la toma de decisiones en todos los niveles | D9: =IFERROR(INDEX(OKR_ROLLUP!$K:$K, MATCH($B9, OKR_ROLLUP!$C:$C, 0)),"") -> V | E9: =IFERROR(INDEX(OKR_ROLLUP!$M:$M, MATCH($B9, OKR_ROLLUP!$C:$C, 0)),"") -> → | F9: =IFERROR(INDEX(OKR_ROLLUP!$N:$N, MATCH($B9, OKR_ROLLUP!$C:$C, 0)),"") -> Alta | G9: =IFERROR(INDEX(OKR_ROLLUP!$O:$O, MATCH($B9, OKR_ROLLUP!$C:$C, 0)),"") -> Monitoreando | H9: =IFERROR(INDEX(OKR_ROLLUP!$P:$P, MATCH($B9, OKR_ROLLUP!$C:$C, 0)),"") -> 0
B10: 6 | C10: =IFERROR(INDEX(OKR_ROLLUP!$D:$D, MATCH($B10, OKR_ROLLUP!$C:$C, 0)),"") -> Fortalecer la resiliencia organizacional y una cultura de riesgo ética y proactiva | D10: =IFERROR(INDEX(OKR_ROLLUP!$K:$K, MATCH($B10, OKR_ROLLUP!$C:$C, 0)),"") -> V | E10: =IFERROR(INDEX(OKR_ROLLUP!$M:$M, MATCH($B10, OKR_ROLLUP!$C:$C, 0)),"") -> ↓ | F10: =IFERROR(INDEX(OKR_ROLLUP!$N:$N, MATCH($B10, OKR_ROLLUP!$C:$C, 0)),"") -> Alta | G10: =IFERROR(INDEX(OKR_ROLLUP!$O:$O, MATCH($B10, OKR_ROLLUP!$C:$C, 0)),"") -> Monitoreando | H10: =IFERROR(INDEX(OKR_ROLLUP!$P:$P, MATCH($B10, OKR_ROLLUP!$C:$C, 0)),"") -> 0
B11: 7 | C11: =IFERROR(INDEX(OKR_ROLLUP!$D:$D, MATCH($B11, OKR_ROLLUP!$C:$C, 0)),"") -> Generación de Liderazgo Estratégico y Adaptativo | D11: =IFERROR(INDEX(OKR_ROLLUP!$K:$K, MATCH($B11, OKR_ROLLUP!$C:$C, 0)),"") -> V | E11: =IFERROR(INDEX(OKR_ROLLUP!$M:$M, MATCH($B11, OKR_ROLLUP!$C:$C, 0)),"") -> ↑ | F11: =IFERROR(INDEX(OKR_ROLLUP!$N:$N, MATCH($B11, OKR_ROLLUP!$C:$C, 0)),"") -> Alta | G11: =IFERROR(INDEX(OKR_ROLLUP!$O:$O, MATCH($B11, OKR_ROLLUP!$C:$C, 0)),"") -> Monitoreando | H11: =IFERROR(INDEX(OKR_ROLLUP!$P:$P, MATCH($B11, OKR_ROLLUP!$C:$C, 0)),"") -> 0
B12: 8 | C12: =IFERROR(INDEX(OKR_ROLLUP!$D:$D, MATCH($B12, OKR_ROLLUP!$C:$C, 0)),"") -> Gobernanza orientada a la Sostenibilidad Corporativa | D12: =IFERROR(INDEX(OKR_ROLLUP!$K:$K, MATCH($B12, OKR_ROLLUP!$C:$C, 0)),"") -> V | E12: =IFERROR(INDEX(OKR_ROLLUP!$M:$M, MATCH($B12, OKR_ROLLUP!$C:$C, 0)),"") -> → | F12: =IFERROR(INDEX(OKR_ROLLUP!$N:$N, MATCH($B12, OKR_ROLLUP!$C:$C, 0)),"") -> Alta | G12: =IFERROR(INDEX(OKR_ROLLUP!$O:$O, MATCH($B12, OKR_ROLLUP!$C:$C, 0)),"") -> Monitoreando | H12: =IFERROR(INDEX(OKR_ROLLUP!$P:$P, MATCH($B12, OKR_ROLLUP!$C:$C, 0)),"") -> 0
B14: Watchlist Horizonte (KRs 3 años) — Top 1–5
B15: Rank | C15: KR 3 años | D15: Cobertura | E15: Estatus (V/A/R) | F15: Próximo checkpoint | G15: Mensaje 1 línea | H15: Solicitud/Decisión
B16: 1 | C16: =IFERROR(INDEX(ALINEACIÓN_2028_a_2026!$C:$C, MATCH($B16, ALINEACIÓN_2028_a_2026!$I:$I, 0)),"") -> Mejorar eficiencia operativa al 30% | D16: =IFERROR(INDEX(ALINEACIÓN_2028_a_2026!$F:$F, MATCH($B16, ALINEACIÓN_2028_a_2026!$I:$I, 0)),"") -> Cubierto | E16: =IFERROR(INDEX(ALINEACIÓN_2028_a_2026!$J:$J, MATCH($B16, ALINEACIÓN_2028_a_2026!$I:$I, 0)),"") -> R | F16: =IFERROR(INDEX(ALINEACIÓN_2028_a_2026!$K:$K, MATCH($B16, ALINEACIÓN_2028_a_2026!$I:$I, 0)),"") -> 46081 | G16: =IFERROR(INDEX(ALINEACIÓN_2028_a_2026!$L:$L, MATCH($B16, ALINEACIÓN_2028_a_2026!$I:$I, 0)),"") -> Externo Analysis del Problema activado | H16: =IFERROR(INDEX(ALINEACIÓN_2028_a_2026!$M:$M, MATCH($B16, ALINEACIÓN_2028_a_2026!$I:$I, 0)),"") -> Aprobar plan de correction de corto plazo
B17: 2 | C17: =IFERROR(INDEX(ALINEACIÓN_2028_a_2026!$C:$C, MATCH($B17, ALINEACIÓN_2028_a_2026!$I:$I, 0)),"") -> Aumentar Participación de Mercado 3.6 a 4.5% | D17: =IFERROR(INDEX(ALINEACIÓN_2028_a_2026!$F:$F, MATCH($B17, ALINEACIÓN_2028_a_2026!$I:$I, 0)),"") -> Cubierto | E17: =IFERROR(INDEX(ALINEACIÓN_2028_a_2026!$J:$J, MATCH($B17, ALINEACIÓN_2028_a_2026!$I:$I, 0)),"") -> A | F17: =IFERROR(INDEX(ALINEACIÓN_2028_a_2026!$K:$K, MATCH($B17, ALINEACIÓN_2028_a_2026!$I:$I, 0)),"") -> 46099 | G17: =IFERROR(INDEX(ALINEACIÓN_2028_a_2026!$L:$L, MATCH($B17, ALINEACIÓN_2028_a_2026!$I:$I, 0)),"") -> Campana para nuevos socios se debe cambiar a otro mercado basado en resultados preliminares | H17: =IFERROR(INDEX(ALINEACIÓN_2028_a_2026!$M:$M, MATCH($B17, ALINEACIÓN_2028_a_2026!$I:$I, 0)),"") -> Aprobar Presupuesto y establecer gatillos de escalamiento
B18: 3 | C18: =IFERROR(INDEX(ALINEACIÓN_2028_a_2026!$C:$C, MATCH($B18, ALINEACIÓN_2028_a_2026!$I:$I, 0)),"") -> Mantener NPS a 8 | D18: =IFERROR(INDEX(ALINEACIÓN_2028_a_2026!$F:$F, MATCH($B18, ALINEACIÓN_2028_a_2026!$I:$I, 0)),"") -> Cubierto | E18: =IFERROR(INDEX(ALINEACIÓN_2028_a_2026!$J:$J, MATCH($B18, ALINEACIÓN_2028_a_2026!$I:$I, 0)),"") -> V | F18: =IFERROR(INDEX(ALINEACIÓN_2028_a_2026!$K:$K, MATCH($B18, ALINEACIÓN_2028_a_2026!$I:$I, 0)),"") -> 46120 | G18: =IFERROR(INDEX(ALINEACIÓN_2028_a_2026!$L:$L, MATCH($B18, ALINEACIÓN_2028_a_2026!$I:$I, 0)),"") -> Monitoreando | H18: =IFERROR(INDEX(ALINEACIÓN_2028_a_2026!$M:$M, MATCH($B18, ALINEACIÓN_2028_a_2026!$I:$I, 0)),"") -> 0
B19: 4 | C19: =IFERROR(INDEX(ALINEACIÓN_2028_a_2026!$C:$C, MATCH($B19, ALINEACIÓN_2028_a_2026!$I:$I, 0)),"") -> Incrementar activos totales a MXN $21 mil mdp | D19: =IFERROR(INDEX(ALINEACIÓN_2028_a_2026!$F:$F, MATCH($B19, ALINEACIÓN_2028_a_2026!$I:$I, 0)),"") -> Cubierto | E19: =IFERROR(INDEX(ALINEACIÓN_2028_a_2026!$J:$J, MATCH($B19, ALINEACIÓN_2028_a_2026!$I:$I, 0)),"") -> A | F19: =IFERROR(INDEX(ALINEACIÓN_2028_a_2026!$K:$K, MATCH($B19, ALINEACIÓN_2028_a_2026!$I:$I, 0)),"") -> 46080 | G19: =IFERROR(INDEX(ALINEACIÓN_2028_a_2026!$L:$L, MATCH($B19, ALINEACIÓN_2028_a_2026!$I:$I, 0)),"") -> Asignacion a Comision Comercial para profundizar entendimiento de los problemas | H19: =IFERROR(INDEX(ALINEACIÓN_2028_a_2026!$M:$M, MATCH($B19, ALINEACIÓN_2028_a_2026!$I:$I, 0)),"") -> Establecer prioridades para los cambios del plan de captacion
B20: 5 | C20: =IFERROR(INDEX(ALINEACIÓN_2028_a_2026!$C:$C, MATCH($B20, ALINEACIÓN_2028_a_2026!$I:$I, 0)),"") -> Mantener mora <=8% | D20: =IFERROR(INDEX(ALINEACIÓN_2028_a_2026!$F:$F, MATCH($B20, ALINEACIÓN_2028_a_2026!$I:$I, 0)),"") -> Requiere Proxy Año 1 | E20: =IFERROR(INDEX(ALINEACIÓN_2028_a_2026!$J:$J, MATCH($B20, ALINEACIÓN_2028_a_2026!$I:$I, 0)),"") -> A | F20: =IFERROR(INDEX(ALINEACIÓN_2028_a_2026!$K:$K, MATCH($B20, ALINEACIÓN_2028_a_2026!$I:$I, 0)),"") -> 46112 | G20: =IFERROR(INDEX(ALINEACIÓN_2028_a_2026!$L:$L, MATCH($B20, ALINEACIÓN_2028_a_2026!$I:$I, 0)),"") -> Cobranza perdio 15% de la estructura este mes | H20: =IFERROR(INDEX(ALINEACIÓN_2028_a_2026!$M:$M, MATCH($B20, ALINEACIÓN_2028_a_2026!$I:$I, 0)),"") -> Aprovar proveedor para corto plazo

Sheet MASTER_2028_KRs
A1: MASTER 2028 — KRs 3 años (Referencia)
A2: Referencia para mantener línea de vista. La operación mensual se gestiona por el Watchlist Horizonte.
A4: # DE LA INTENCION | B4: Desc Intención | C4: KR # | D4: KR ID | E4: KR DESCRIPCION | F4: RESPONSABLE | G4: META 2028 | H4: REAL OCT. 2025 | I4: REAL ACUM OCT. 2025 | J4: META 2026 | K4: META 1Q 2026 | L4: CRITERIOS DE SEMAFORACIZACION
A5: 1 | B5: Capacidad Transformacional y Diferenciada | C5: 1 | D5: KR 1 | E5: Mejorar eficiencia operativa al 30% | F5: DG - C. Gerencial (FT: Alejandro Lomelí) | G5: 0.3 | J5: 0.472 | L5: PUNTO DE DOLOR MAXIMO TOPE DE TOLERANCIA = ROLJO
A6: 1 | B6: Capacidad Transformacional y Diferenciada | C6: 2 | D6: KR 2 | E6: Aumentar Participación de Mercado 3.6 a 4.5% (21 mil millones - sector / activos totales) | F6: Arturo Ramírez - José Zeferino Ruíz | G6: De 3.6 a 4.5% | J6: 0.0402
A7: 1 | B7: Capacidad Transformacional y Diferenciada | C7: 3 | D7: KR 3 | E7: KR3 - Mantener NPS a 8 | F7: Arturo Ramírez - Aldo Ramírez | G7: 8 | J7: 8
A8: 2 | B8: Crecimiento e Impacto de Mercado | C8: 4 | D8: KR 1 | E8: Incrementar los activos totales a MXN $21 mil millones de forma acumulada | F8: Arturo Ramírez - José Zeferino Ruíz | G8: MXN $21 mil millones | J8: MXN $15,270 | L8: PUNTO DE DOLOR MAXIMO TOPE DE TOLERANCIA = ROLJO
A9: 2 | B9: Crecimiento e Impacto de Mercado | C9: 5 | D9: KR 2 | E9: Mantener calidad de cartera (mora) no mayor al 8% | F9: Javier Gutiérrez | J9: 0.0947 | L9: PUNTO DE DOLOR MAXIMO TOPE DE TOLERANCIA = ROLJO
A10: 2 | B10: Crecimiento e Impacto de Mercado | C10: 6 | D10: KR 3 | E10: Crecer en 100,000 nuevos socios activos* | F10: Arturo Ramírez - José Zeferino Ruíz | G10: 100,000 nuevos socios activos | J10: 33333
A11: 2 | B11: Crecimiento e Impacto de Mercado | C11: 7 | D11: KR 4 | E11: Alcanzar 50% (50,000) de los nuevos socios activos pertenezcan al segmento joven | F11: Arturo Ramírez - José Zeferino Ruíz | G11: 50% (50,000) socios activos segmento jóven | J11: 16700
A12: 2 | B12: Crecimiento e Impacto de Mercado | C12: 8 | D12: KR 5 | E12: Alcanzar 25% o 12,500 de los socios jóvenes por canal dig. (nuevos y actuales) | F12: Arturo Ramírez - Aldo Ramírez | G12: 25% o 12,500 socios jóvenes | J12: 3000
A13: 2 | B13: Crecimiento e Impacto de Mercado | C13: 9 | D13: KR 6 | E13: Mantener un Retorno sobre Activos (ROA) del 5% | F13: DG - C. Gerencial (FT: Alejandro Lomelí) | G13: 0.05 | J13: 0.034
A14: 3 | B14: Establecer una robusta y efectiva gestión y cultura de riesgos | C14: 10 | D14: KR 1 | E14: Porcentaje de riesgos con límites cuantificados bajo modelos avanzados, 100% (año 3) | F14: Javier Gutiérrez | G14: 100% (año 3) | J14: 100% del plan definido y aprobado año 1
A15: 3 | B15: Establecer una robusta y efectiva gestión y cultura de riesgos | C15: 11 | D15: KR 2 | E15: Pérdidas operacionales respecto de ingresos operacionales <=1.5% | F15: Javier Gutiérrez | G15: <=1.5% | J15: Tope: <=1.5% ($55mdp)
A16: 3 | B16: Establecer una robusta y efectiva gestión y cultura de riesgos | C16: 12 | D16: KR 3 | E16: Porcentaje de eventos identificados en fase temprana (antes de materialización): 50% (año 1), 75% (año 2), 100% (año 3) | F16: Javier Gutiérrez | G16: Año 1: 50% Año 2: 75% Año 3: 100% | J16: 0.5
A17: 4 | B17: Cultura y gobernanza saludable y sostenible | C17: 13 | D17: KR 1 | E17: Mantener eNPS de 9 de 10 | F17: Erika Arellano - Elizabeth Sánchez | G17: 9 | J17: 8.6
A18: 4 | B18: Cultura y gobernanza saludable y sostenible | C18: 14 | D18: KR 2 | E18: Mantener 95% Plan de Sucesión de Puestos clave | F18: Erika Arellano - Andrea Silva | G18: 0.95 | J18: 0.8
A19: 4 | B19: Cultura y gobernanza saludable y sostenible | C19: 15 | D19: KR 3 | E19: Alcanzar el Índice de Salud Organizacional Integral de .3% | F19: Erika Arellano - Elizabeth Sánchez | G19: 0.003 | J19: 0.001
A20: 4 | C20: 16 | D20: KR 4.4 | E20: • KR4.4 Clima Laboral Global (SOI-CLG) 2026 | F20: Erika Arellano - Elizabeth Sánchez | G20: 0.75 | J20: 0.71
A21: 4 | C21: 17 | D21: KR 7 | E21: • KR7. Indice de Rotación de Personal (SOI-IRP) 2026 | F21: Erika Arellano - Elizabeth Sánchez | G21: 0.2 | J21: 0.25
A22: 4 | C22: 18 | D22: KR 4.1 | E22: • KR4.1 Alcanzar Avance** Plan estratégico 80% | F22: Myriam Hernandez | G22: TBD | J22: 0.8
